danielle/__init__.py
danielle/__main__.py
danielle/array.py
danielle/circular_linked_list.py
danielle/doubly_linked_list.py
danielle/graph.py
danielle/linked_list.py
danielle/queue.py
danielle/stack.py
danielle/tree.py
danielle-0.1.0.dist-info/licenses/LICENSE
danielle-0.1.0.dist-info/METADATA
danielle-0.1.0.dist-info/WHEEL
danielle-0.1.0.dist-info/top_level.txt
danielle-0.1.0.dist-info/RECORD
