Metadata-Version: 2.4
Name: danielle
Version: 0.1.0
Summary: A Python package implementing core data structures from scratch
Home-page: https://github.com/dany237/data_structures
Author: Kapsa Danielle
Author-email: adeandkofi@gmail.com
Classifier: Programming Language :: Python :: 3
Classifier: License :: OSI Approved :: MIT License
Classifier: Operating System :: OS Independent
Requires-Python: >=3.7
License-File: LICENSE
Dynamic: author
Dynamic: author-email
Dynamic: classifier
Dynamic: description
Dynamic: description-content-type
Dynamic: home-page
Dynamic: license-file
Dynamic: requires-python
Dynamic: summary
